{
  "0": {
    "basicblocks": 15,
    "calls": "1 2",
    "file": "hart.cpp",
    "fileloc": 4,
    "instructions": 604,
    "loads": {
      "G": 4,
      "L": 31
    },
    "name": "hart",
    "stores": {
      "G": 6,
      "L": 30
    },
    "total_instructions": 6972
  },
  "1": {
    "basicblocks": 25,
    "calls": "",
    "file": "OP_AL_B.cpp",
    "fileloc": 3,
    "instructions": 142,
    "loads": {
      "L": 14
    },
    "name": "OP_AL_32B",
    "stores": {
      "L": 14
    },
    "total_instructions": 423
  },
  "2": {
    "basicblocks": 76,
    "calls": "",
    "file": "OP_AL_32I.cpp",
    "fileloc": 5,
    "instructions": 503,
    "loads": {
      "L": 32
    },
    "name": "OP_AL_32I",
    "stores": {
      "L": 32
    },
    "total_instructions": 3311
  }
}